auglab/add_trainer.py
auglab/configs/__init__.py
auglab/trainers/__init__.py
auglab/trainers/nnUNetTrainerDAExt.py
auglab/trainers/nnUNetTrainerTest.py
auglab/trainers/utils.py
auglab/transforms/cpu/artifact.py
auglab/transforms/cpu/contrast.py
auglab/transforms/cpu/fromSeg.py
auglab/transforms/cpu/spatial.py
auglab/transforms/cpu/transforms.py
auglab/transforms/gpu/base.py
auglab/transforms/gpu/contrast.py
auglab/transforms/gpu/fromSeg.py
auglab/transforms/gpu/spatial.py
auglab/transforms/gpu/transforms.py
auglab/utils/image.py
auglab/utils/utils.py
auglab-20260109.dist-info/licenses/LICENSE
auglab-20260109.dist-info/METADATA
auglab-20260109.dist-info/WHEEL
auglab-20260109.dist-info/entry_points.txt
auglab-20260109.dist-info/top_level.txt
auglab-20260109.dist-info/RECORD
