Metadata-Version: 2.4
Name: auglab
Version: 20260109
Summary: AugLab investigates the influence of different data augmentation strategies on MRI training performance.
Author: Hendrik Möller
Author-email: Nathan Molinier <nathan.molinier@polymtl.ca>
Project-URL: homepage, https://github.com/neuropoly/AugLab
Project-URL: repository, https://github.com/neuropoly/AugLab
Keywords: deep learning,image segmentation,nnU-Net,nnunet,magnetic resonance imaging,online augmentation,offline augmentation,mri
Classifier: Development Status :: 5 - Production/Stable
Classifier: Intended Audience :: Science/Research
Classifier: Programming Language :: Python :: 3
Classifier: Topic :: Scientific/Engineering :: Artificial Intelligence
Classifier: Topic :: Scientific/Engineering :: Image Recognition
Classifier: Topic :: Scientific/Engineering :: Medical Science Apps.
Requires-Python: >=3.10
License-File: LICENSE
Requires-Dist: batchgeneratorsv2
Requires-Dist: kornia
Provides-Extra: nnunetv2
Requires-Dist: nnunetv2; extra == "nnunetv2"
Provides-Extra: all
Requires-Dist: torchio; extra == "all"
Requires-Dist: monai[all]; extra == "all"
Requires-Dist: progress; extra == "all"
Requires-Dist: numpy; extra == "all"
Requires-Dist: tqdm; extra == "all"
Requires-Dist: wandb; extra == "all"
Dynamic: license-file
